arangopipe/Dockerfile_Prod
arangopipe/Dockerfile_TFFE
arangopipe/Dockerfile_Torch_FE
arangopipe/MANIFEST.in
arangopipe/__init__.py
arangopipe/arangopipe_examples.ipynb
arangopipe/arangopipe_examples_torch.ipynb
arangopipe/makefile
arangopipe/prod_startup_commands.sh
arangopipe/startup_commands.sh
arangopipe/aisis-foxx/aisis-foxx.zip
arangopipe/aisis-foxx/passwd.txt
arangopipe/arangopipe_analytics/__init__.py
arangopipe/arangopipe_analytics/dataset_shift_detector.py
arangopipe/arangopipe_analytics/rf_dataset_shift_detector.py
arangopipe/arangopipe_storage/__init__.py
arangopipe/arangopipe_storage/arangopipe_admin_api.py
arangopipe/arangopipe_storage/arangopipe_api.py
arangopipe/arangopipe_storage/arangopipe_config.py
arangopipe/arangopipe_storage/arangopipe_config.yaml
arangopipe/arangopipe_storage/connection_manager.py
arangopipe/arangopipe_storage/managed_service_conn_parameters.py
arangopipe-0.0.70.0.2.dist-info/METADATA
arangopipe-0.0.70.0.2.dist-info/WHEEL
arangopipe-0.0.70.0.2.dist-info/top_level.txt
arangopipe-0.0.70.0.2.dist-info/RECORD
