Metadata-Version: 2.1
Name: arangopipe
Version: 0.0.70.0.2
Summary: package for machine learning meta-data management and analysis
Home-page: https://github.com/arangoml/arangopipe
Author: ArangoDB
Author-email: joerg@arangodb.com
License: Apache
Platform: UNKNOWN
Classifier: License :: OSI Approved :: Apache Software License
Classifier: Programming Language :: Python :: 3
Classifier: Programming Language :: Python :: 3.7
